sphinxcontrib_redirects-0.2.0-py3.12-nspkg.pth
sphinxcontrib/redirects/__init__.py
sphinxcontrib_redirects-0.2.0.dist-info/AUTHORS
sphinxcontrib_redirects-0.2.0.dist-info/LICENSE
sphinxcontrib_redirects-0.2.0.dist-info/METADATA
sphinxcontrib_redirects-0.2.0.dist-info/WHEEL
sphinxcontrib_redirects-0.2.0.dist-info/namespace_packages.txt
sphinxcontrib_redirects-0.2.0.dist-info/pbr.json
sphinxcontrib_redirects-0.2.0.dist-info/top_level.txt
sphinxcontrib_redirects-0.2.0.dist-info/RECORD
