Metadata-Version: 2.1
Name: sphinxcontrib-redirects
Version: 0.2.0
Summary: Sphinx extension to generate JavaScript-driven redirects for moved pages
Home-page: https://github.com/sphinx-contrib/sphinxcontrib-redirects
Author: Stephen Finucane
Author-email: stephen@that.guru
Project-URL: Bug Tracker, https://github.com/sphinx-contrib/redirects/issues
Project-URL: Source Code, https://github.com/sphinx-contrib/redirects
Keywords: sphinx
Classifier: Development Status :: 4 - Beta
Classifier: Environment :: Console
Classifier: Intended Audience :: Developers
Classifier: Intended Audience :: Information Technology
Classifier: License :: OSI Approved :: BSD License
Classifier: Operating System :: OS Independent
Classifier: Programming Language :: Python
Classifier: Programming Language :: Python :: 3
Classifier: Programming Language :: Python :: 3 :: Only
Classifier: Topic :: Documentation
Classifier: Topic :: Utilities
Requires-Python: >=3.9
License-File: LICENSE
License-File: AUTHORS
Requires-Dist: sphinx >=7.0.0
Provides-Extra: sphinx
Requires-Dist: sphinx ; extra == 'sphinx'
Provides-Extra: test
Requires-Dist: pytest ; extra == 'test'
